{
  "timeline": [
    {
      "year": "2024 — HIỆN TẠI",
      "title": "Product Engineer & Solo Builder",
      "desc": "Xây dựng các sản phẩm AI-native từ đầu đến cuối. Kỹ sư fullstack chuyển sang làm sản phẩm."
    },
    {
      "year": "2021 — 2024",
      "title": "Kỹ sư Phần mềm Cao cấp",
      "desc": "Ship các hệ thống production xuyên suốt frontend, backend, và hạ tầng."
    },
    {
      "year": "2019 — 2021",
      "title": "Kỹ sư Phần mềm",
      "desc": "Xây dựng hệ thống dữ liệu thời gian thực và nền tảng API cho sản phẩm giai đoạn đầu."
    },
    {
      "year": "2017 — 2019",
      "title": "Lập trình viên Junior",
      "desc": "Xây dựng công cụ và hạ tầng web cho hệ thống suy luận ML."
    }
  ]
}
